code_faster/__init__.py
code_faster/fetcher.py
code_faster/runner.py
code_faster/utils.py
code_faster/version.py
code_faster/fetchers/__init__.py
code_faster/fetchers/base_fetcher.py
code_faster/fetchers/cc_fetcher.py
code_faster/fetchers/cf_fetcher.py
code_faster/fetchers/fetcher_factory.py
code_faster/fetchers/spoj_fetcher.py
code_faster/runners/__init__.py
code_faster/runners/base_runner.py
code_faster/runners/cpp_runner.py
code_faster/runners/java_runner.py
code_faster/runners/py_runner.py
code_faster/runners/runner_factory.py
code_faster/sample/cpp/main.cpp
code_faster/sample/java/Main.java
code_faster/sample/py/main.py
code_faster-0.4.1.dist-info/LICENSE
code_faster-0.4.1.dist-info/METADATA
code_faster-0.4.1.dist-info/WHEEL
code_faster-0.4.1.dist-info/entry_points.txt
code_faster-0.4.1.dist-info/top_level.txt
code_faster-0.4.1.dist-info/RECORD
