Metadata-Version: 2.1
Name: code-faster
Version: 0.4.1
Summary: A cross-platform command line utility for bootstrapping and running code with tests
Home-page: https://github.com/rahulsrma26/code_faster
Author: Rahul Sharma
Author-email: rahulsrma26@gmail.com
Maintainer: rahulsrma26
Maintainer-email: welcometors@gmail.com
License: LICENSE
Project-URL: Code, https://github.com/rahulsrma26/code_faster
Keywords: codeforces runner setuptools development
Platform: UNKNOWN
Classifier: Programming Language :: Python :: 3
Classifier: Programming Language :: Python :: 3.6
Classifier: Programming Language :: Python :: 3.7
Classifier: Programming Language :: Python :: 3.8
Classifier: Programming Language :: Python :: 3 :: Only
Classifier: License :: OSI Approved :: MIT License
Classifier: Operating System :: OS Independent
Classifier: Topic :: Software Development :: Code Generators
Classifier: Topic :: Software Development :: Libraries :: Python Modules
Classifier: Topic :: Software Development :: Testing :: Unit
Requires-Python: >=3.6
Requires-Dist: requests
Requires-Dist: beautifulsoup4
Requires-Dist: colorama
Provides-Extra: dev
Requires-Dist: check-manifestpytest ; extra == 'dev'
Requires-Dist: coverage ; extra == 'dev'
Requires-Dist: tox ; extra == 'dev'
